tool_simulation/__init__.py
tool_simulation/core/__init__.py
tool_simulation/core/aistudio_backend.py
tool_simulation/core/aistudio_prompt_builder.py
tool_simulation/core/aistudio_prompt_builder_test.py
tool_simulation/core/base_prompt_builder.py
tool_simulation/core/base_prompt_builder_test.py
tool_simulation/core/gemma_prompt_builder.py
tool_simulation/core/gemma_prompt_builder_test.py
tool_simulation/core/llama_prompt_builder.py
tool_simulation/core/llama_prompt_builder_test.py
tool_simulation/core/model_instance.py
tool_simulation/core/proto2tool.py
tool_simulation/core/proto2tool_test.py
tool_simulation/core/str2call.py
tool_simulation/core/str2call_test.py
tool_simulation/core/testing_utils.py
tool_simulation/core/tool2str.py
tool_simulation/core/tool2str_test.py
tool_simulation/core/tool_types.py
tool_simulation/pipelines/__init__.py
tool_simulation/pipelines/base_pipeline.py
tool_simulation/stages/data_generation/__init__.py
tool_simulation/stages/data_generation/seed_data.py
tool_simulation/stages/data_generation/seed_data_test.py
tool_simulation/stages/exports/__init__.py
tool_simulation/stages/exports/export_hf_chat.py
tool_simulation/stages/exports/export_hf_chat_test.py
tool_simulation/stages/exports/export_tf_example.py
tool_simulation/stages/exports/export_tf_example_test.py
tool_simulation/stages/function_calling/__init__.py
tool_simulation/stages/function_calling/datagen_prompt_builder.py
tool_simulation/stages/function_calling/datagen_prompt_builder_test.py
tool_simulation/stages/function_calling/function_calling_episode.py
tool_simulation/stages/function_calling/function_calling_episode_test.py
tool_simulation/stages/function_calling/replier_prompt_builder.py
tool_simulation/stages/function_calling/replier_prompt_builder_test.py
tool_simulation/stages/function_calling/session.py
tool_simulation/stages/testing_utils/testing_commons.py
tool_simulation/stages/utils/__init__.py
tool_simulation/stages/utils/margin.py
ai_edge_tool_simulation-0.1.0.post1.dist-info/METADATA
ai_edge_tool_simulation-0.1.0.post1.dist-info/WHEEL
ai_edge_tool_simulation-0.1.0.post1.dist-info/top_level.txt
ai_edge_tool_simulation-0.1.0.post1.dist-info/RECORD
