Metadata-Version: 2.4
Name: ai-edge-tool-simulation
Version: 0.1.0.post1
Summary: Library for simulating tool use, function calling, and data generation/validation for language models.
License-Expression: Apache-2.0
Classifier: Development Status :: 3 - Alpha
Classifier: Intended Audience :: Developers
Classifier: Programming Language :: Python
Classifier: Programming Language :: Python :: 3
Classifier: Programming Language :: Python :: 3.9
Classifier: Programming Language :: Python :: 3.10
Classifier: Programming Language :: Python :: 3.11
Classifier: Programming Language :: Python :: 3.12
Classifier: Topic :: Scientific/Engineering :: Artificial Intelligence
Classifier: Topic :: Software Development :: Libraries :: Python Modules
Requires-Python: >=3.9
Requires-Dist: absl-py
Requires-Dist: google-genai
Requires-Dist: proto-plus
Requires-Dist: tensorflow
